rankset/__init__.py
rankset/sampler.py
rankset/utils.py
rankest-0.1.0.dist-info/METADATA
rankest-0.1.0.dist-info/WHEEL
rankest-0.1.0.dist-info/top_level.txt
rankest-0.1.0.dist-info/RECORD
