Metadata-Version: 2.4
Name: rankest
Version: 0.1.0
Summary: A package for Rank Set Sampling using sum‑based ranking
Author: T. Vaishnavi
Author-email: tvaishu13@gmail.com
Maintainer: Neha Singh
Classifier: Programming Language :: Python :: 3
Classifier: License :: OSI Approved :: MIT License
Classifier: Operating System :: OS Independent
Requires-Python: >=3.6
Requires-Dist: pandas
Dynamic: author
Dynamic: author-email
Dynamic: classifier
Dynamic: description
Dynamic: description-content-type
Dynamic: maintainer
Dynamic: requires-dist
Dynamic: requires-python
Dynamic: summary
